linkml_runtime_api/__init__.py
linkml_runtime_api/apiroot.py
linkml_runtime_api/changer/__init__.py
linkml_runtime_api/changer/changer.py
linkml_runtime_api/changer/changes.yaml
linkml_runtime_api/changer/changes_model.py
linkml_runtime_api/changer/jsonpatch_changer.py
linkml_runtime_api/changer/object_changer.py
linkml_runtime_api/diffs/__init__.py
linkml_runtime_api/diffs/differ.py
linkml_runtime_api/diffs/yaml_patch.py
linkml_runtime_api/generators/__init__.py
linkml_runtime_api/generators/apigenerator.py
linkml_runtime_api/generators/fastapigenerator.py
linkml_runtime_api/generators/pyapigenerator.py
linkml_runtime_api/query/__init__.py
linkml_runtime_api/query/object_queryengine.py
linkml_runtime_api/query/query.yaml
linkml_runtime_api/query/query_model.py
linkml_runtime_api/query/queryengine.py
linkml_runtime_api-0.0.6.dist-info/AUTHORS
linkml_runtime_api-0.0.6.dist-info/METADATA
linkml_runtime_api-0.0.6.dist-info/WHEEL
linkml_runtime_api-0.0.6.dist-info/entry_points.txt
linkml_runtime_api-0.0.6.dist-info/top_level.txt
linkml_runtime_api-0.0.6.dist-info/RECORD
